shlib/__init__.py
shlib/extended_pathlib.py
shlib/shlib.py
shlib-1.8.dist-info/licenses/LICENSE
shlib-1.8.dist-info/WHEEL
shlib-1.8.dist-info/METADATA
shlib-1.8.dist-info/RECORD
