Metadata-Version: 2.4
Name: shlib
Version: 1.8
Summary: shell library
Keywords: shlib,shell,shell utilities
Author: Ken Kundert
Author-email: shlib@nurdletech.com
Requires-Python: >=3.6
Classifier: Development Status :: 5 - Production/Stable
Classifier: Intended Audience :: Developers
Classifier: License :: OSI Approved :: MIT License
Classifier: Natural Language :: English
Classifier: Operating System :: POSIX :: Linux
Classifier: Programming Language :: Python :: 3
Classifier: Topic :: Utilities
License-File: LICENSE
Requires-Dist: braceexpand
Requires-Dist: inform>=1.28
Project-URL: documentation, https://github.com/kenkundert/shlib
Project-URL: homepage, https://github.com/kenkundert/shlib
Project-URL: repository, https://github.com/kenkundert/shlib
